[
  {
    "type": "constructor",
    "inputs": [
      {
        "name": "initialOwner",
        "type": "address",
        "internalType": "address"
      }
    ],
    "stateMutability": "nonpayable"
  },
  {
    "type": "function",
    "name": "accessControlModule",
    "inputs": [],
    "outputs": [
      {
        "name": "",
        "type": "address",
        "internalType": "address"
      }
    ],
    "stateMutability": "view"
  },
  {
    "type": "function",
    "name": "agentTokenModule",
    "inputs": [],
    "outputs": [
      {
        "name": "",
        "type": "address",
        "internalType": "address"
      }
    ],
    "stateMutability": "view"
  },
  {
    "type": "function",
    "name": "calculateTokenHolderRevenue",
    "inputs": [
      {
        "name": "agentId",
        "type": "uint256",
        "internalType": "uint256"
      },
      {
        "name": "account",
        "type": "address",
        "internalType": "address"
      }
    ],
    "outputs": [
      {
        "name": "",
        "type": "uint256",
        "internalType": "uint256"
      }
    ],
    "stateMutability": "view"
  },
  {
    "type": "function",
    "name": "claimAgentRevenue",
    "inputs": [
      {
        "name": "agentId",
        "type": "uint256",
        "internalType": "uint256"
      }
    ],
    "outputs": [],
    "stateMutability": "nonpayable"
  },
  {
    "type": "function",
    "name": "claimTokenHolderRevenue",
    "inputs": [
      {
        "name": "agentId",
        "type": "uint256",
        "internalType": "uint256"
      }
    ],
    "outputs": [],
    "stateMutability": "nonpayable"
  },
  {
    "type": "function",
    "name": "claimTokenHolderRevenueProportional",
    "inputs": [
      {
        "name": "agentId",
        "type": "uint256",
        "internalType": "uint256"
      }
    ],
    "outputs": [],
    "stateMutability": "nonpayable"
  },
  {
    "type": "function",
    "name": "claimTreasuryRevenue",
    "inputs": [
      {
        "name": "agentId",
        "type": "uint256",
        "internalType": "uint256"
      }
    ],
    "outputs": [],
    "stateMutability": "nonpayable"
  },
  {
    "type": "function",
    "name": "depositRevenue",
    "inputs": [
      {
        "name": "agentId",
        "type": "uint256",
        "internalType": "uint256"
      },
      {
        "name": "amount",
        "type": "uint256",
        "internalType": "uint256"
      }
    ],
    "outputs": [],
    "stateMutability": "payable"
  },
  {
    "type": "function",
    "name": "distributeRevenue",
    "inputs": [
      {
        "name": "agentId",
        "type": "uint256",
        "internalType": "uint256"
      }
    ],
    "outputs": [],
    "stateMutability": "nonpayable"
  },
  {
    "type": "function",
    "name": "emergencyWithdrawETH",
    "inputs": [],
    "outputs": [],
    "stateMutability": "nonpayable"
  },
  {
    "type": "function",
    "name": "getAccessControlModule",
    "inputs": [],
    "outputs": [
      {
        "name": "",
        "type": "address",
        "internalType": "address"
      }
    ],
    "stateMutability": "view"
  },
  {
    "type": "function",
    "name": "getAgentTokenModule",
    "inputs": [],
    "outputs": [
      {
        "name": "",
        "type": "address",
        "internalType": "address"
      }
    ],
    "stateMutability": "view"
  },
  {
    "type": "function",
    "name": "getClaimableRevenue",
    "inputs": [
      {
        "name": "agentId",
        "type": "uint256",
        "internalType": "uint256"
      },
      {
        "name": "account",
        "type": "address",
        "internalType": "address"
      }
    ],
    "outputs": [
      {
        "name": "",
        "type": "uint256",
        "internalType": "uint256"
      }
    ],
    "stateMutability": "view"
  },
  {
    "type": "function",
    "name": "getRevenueDistribution",
    "inputs": [
      {
        "name": "agentId",
        "type": "uint256",
        "internalType": "uint256"
      }
    ],
    "outputs": [
      {
        "name": "",
        "type": "tuple",
        "internalType": "struct IRevenueVault.RevenueDistribution",
        "components": [
          {
            "name": "totalRevenue",
            "type": "uint256",
            "internalType": "uint256"
          },
          {
            "name": "agentShare",
            "type": "uint256",
            "internalType": "uint256"
          },
          {
            "name": "treasuryShare",
            "type": "uint256",
            "internalType": "uint256"
          },
          {
            "name": "tokenHolderShare",
            "type": "uint256",
            "internalType": "uint256"
          },
          {
            "name": "lastDistribution",
            "type": "uint256",
            "internalType": "uint256"
          }
        ]
      }
    ],
    "stateMutability": "view"
  },
  {
    "type": "function",
    "name": "getRevenueVaultModule",
    "inputs": [],
    "outputs": [
      {
        "name": "",
        "type": "address",
        "internalType": "address"
      }
    ],
    "stateMutability": "view"
  },
  {
    "type": "function",
    "name": "getTokenHoldersRevenue",
    "inputs": [
      {
        "name": "agentId",
        "type": "uint256",
        "internalType": "uint256"
      }
    ],
    "outputs": [
      {
        "name": "",
        "type": "uint256",
        "internalType": "uint256"
      }
    ],
    "stateMutability": "view"
  },
  {
    "type": "function",
    "name": "laeContract",
    "inputs": [],
    "outputs": [
      {
        "name": "",
        "type": "address",
        "internalType": "contract IERC8004LivingAgent"
      }
    ],
    "stateMutability": "view"
  },
  {
    "type": "function",
    "name": "owner",
    "inputs": [],
    "outputs": [
      {
        "name": "",
        "type": "address",
        "internalType": "address"
      }
    ],
    "stateMutability": "view"
  },
  {
    "type": "function",
    "name": "renounceOwnership",
    "inputs": [],
    "outputs": [],
    "stateMutability": "nonpayable"
  },
  {
    "type": "function",
    "name": "revenueVaultModule",
    "inputs": [],
    "outputs": [
      {
        "name": "",
        "type": "address",
        "internalType": "address"
      }
    ],
    "stateMutability": "view"
  },
  {
    "type": "function",
    "name": "rlmIntegrationContract",
    "inputs": [],
    "outputs": [
      {
        "name": "",
        "type": "address",
        "internalType": "contract IRLMIntegration"
      }
    ],
    "stateMutability": "view"
  },
  {
    "type": "function",
    "name": "setAccessControlModule",
    "inputs": [
      {
        "name": "_accessControlModule",
        "type": "address",
        "internalType": "address"
      }
    ],
    "outputs": [],
    "stateMutability": "nonpayable"
  },
  {
    "type": "function",
    "name": "setAgentTokenModule",
    "inputs": [
      {
        "name": "_agentTokenModule",
        "type": "address",
        "internalType": "address"
      }
    ],
    "outputs": [],
    "stateMutability": "nonpayable"
  },
  {
    "type": "function",
    "name": "setLAEContract",
    "inputs": [
      {
        "name": "_laeContract",
        "type": "address",
        "internalType": "address"
      }
    ],
    "outputs": [],
    "stateMutability": "nonpayable"
  },
  {
    "type": "function",
    "name": "setRLMIntegrationContract",
    "inputs": [
      {
        "name": "_rlmIntegrationContract",
        "type": "address",
        "internalType": "address"
      }
    ],
    "outputs": [],
    "stateMutability": "nonpayable"
  },
  {
    "type": "function",
    "name": "setRevenueVaultModule",
    "inputs": [
      {
        "name": "_revenueVaultModule",
        "type": "address",
        "internalType": "address"
      }
    ],
    "outputs": [],
    "stateMutability": "nonpayable"
  },
  {
    "type": "function",
    "name": "transferOwnership",
    "inputs": [
      {
        "name": "newOwner",
        "type": "address",
        "internalType": "address"
      }
    ],
    "outputs": [],
    "stateMutability": "nonpayable"
  },
  {
    "type": "function",
    "name": "updateDistributionShares",
    "inputs": [
      {
        "name": "agentId",
        "type": "uint256",
        "internalType": "uint256"
      },
      {
        "name": "agentShare",
        "type": "uint256",
        "internalType": "uint256"
      },
      {
        "name": "treasuryShare",
        "type": "uint256",
        "internalType": "uint256"
      },
      {
        "name": "tokenHolderShare",
        "type": "uint256",
        "internalType": "uint256"
      }
    ],
    "outputs": [],
    "stateMutability": "nonpayable"
  },
  {
    "type": "event",
    "name": "AccessControlModuleUpdated",
    "inputs": [
      {
        "name": "previous",
        "type": "address",
        "indexed": true,
        "internalType": "address"
      },
      {
        "name": "current",
        "type": "address",
        "indexed": true,
        "internalType": "address"
      }
    ],
    "anonymous": false
  },
  {
    "type": "event",
    "name": "AgentTokenModuleUpdated",
    "inputs": [
      {
        "name": "previous",
        "type": "address",
        "indexed": true,
        "internalType": "address"
      },
      {
        "name": "current",
        "type": "address",
        "indexed": true,
        "internalType": "address"
      }
    ],
    "anonymous": false
  },
  {
    "type": "event",
    "name": "DistributionSharesUpdated",
    "inputs": [
      {
        "name": "agentId",
        "type": "uint256",
        "indexed": true,
        "internalType": "uint256"
      },
      {
        "name": "agentShare",
        "type": "uint256",
        "indexed": false,
        "internalType": "uint256"
      },
      {
        "name": "treasuryShare",
        "type": "uint256",
        "indexed": false,
        "internalType": "uint256"
      },
      {
        "name": "tokenHolderShare",
        "type": "uint256",
        "indexed": false,
        "internalType": "uint256"
      }
    ],
    "anonymous": false
  },
  {
    "type": "event",
    "name": "LivingAgentRevenueDistributed",
    "inputs": [
      {
        "name": "agentId",
        "type": "uint256",
        "indexed": true,
        "internalType": "uint256"
      },
      {
        "name": "totalRevenue",
        "type": "uint256",
        "indexed": false,
        "internalType": "uint256"
      }
    ],
    "anonymous": false
  },
  {
    "type": "event",
    "name": "OptimalDistributionRatioApplied",
    "inputs": [
      {
        "name": "agentId",
        "type": "uint256",
        "indexed": true,
        "internalType": "uint256"
      },
      {
        "name": "operatorShare",
        "type": "uint256",
        "indexed": false,
        "internalType": "uint256"
      },
      {
        "name": "treasuryShare",
        "type": "uint256",
        "indexed": false,
        "internalType": "uint256"
      },
      {
        "name": "tokenHolderShare",
        "type": "uint256",
        "indexed": false,
        "internalType": "uint256"
      }
    ],
    "anonymous": false
  },
  {
    "type": "event",
    "name": "OwnershipTransferred",
    "inputs": [
      {
        "name": "previousOwner",
        "type": "address",
        "indexed": true,
        "internalType": "address"
      },
      {
        "name": "newOwner",
        "type": "address",
        "indexed": true,
        "internalType": "address"
      }
    ],
    "anonymous": false
  },
  {
    "type": "event",
    "name": "RevenueDeposited",
    "inputs": [
      {
        "name": "agentId",
        "type": "uint256",
        "indexed": true,
        "internalType": "uint256"
      },
      {
        "name": "sender",
        "type": "address",
        "indexed": true,
        "internalType": "address"
      },
      {
        "name": "amount",
        "type": "uint256",
        "indexed": false,
        "internalType": "uint256"
      }
    ],
    "anonymous": false
  },
  {
    "type": "event",
    "name": "RevenueDistributed",
    "inputs": [
      {
        "name": "agentId",
        "type": "uint256",
        "indexed": true,
        "internalType": "uint256"
      },
      {
        "name": "agentAmount",
        "type": "uint256",
        "indexed": false,
        "internalType": "uint256"
      },
      {
        "name": "treasuryAmount",
        "type": "uint256",
        "indexed": false,
        "internalType": "uint256"
      },
      {
        "name": "tokenHoldersAmount",
        "type": "uint256",
        "indexed": false,
        "internalType": "uint256"
      }
    ],
    "anonymous": false
  },
  {
    "type": "event",
    "name": "RevenueVaultModuleUpdated",
    "inputs": [
      {
        "name": "previous",
        "type": "address",
        "indexed": true,
        "internalType": "address"
      },
      {
        "name": "current",
        "type": "address",
        "indexed": true,
        "internalType": "address"
      }
    ],
    "anonymous": false
  },
  {
    "type": "error",
    "name": "OwnableInvalidOwner",
    "inputs": [
      {
        "name": "owner",
        "type": "address",
        "internalType": "address"
      }
    ]
  },
  {
    "type": "error",
    "name": "OwnableUnauthorizedAccount",
    "inputs": [
      {
        "name": "account",
        "type": "address",
        "internalType": "address"
      }
    ]
  },
  {
    "type": "error",
    "name": "ReentrancyGuardReentrantCall",
    "inputs": []
  }
]
